xml_to_acts/__init__.py
xml_to_acts/acts.py
xml_to_acts/cli.py
xml_to_acts/drawio.py
xml_to_acts/node.py
xml_to_acts-1.0.1.dist-info/METADATA
xml_to_acts-1.0.1.dist-info/WHEEL
xml_to_acts-1.0.1.dist-info/entry_points.txt
xml_to_acts-1.0.1.dist-info/top_level.txt
xml_to_acts-1.0.1.dist-info/RECORD
